vox_kafka/__init__.py
vox_kafka/healthcheck/__init__.py
vox_kafka/healthcheck/backends.py
vox_kafka/kafka_client.py
vox_kafka/tests.py
vox_kafka-0.2.3.dist-info/WHEEL
vox_kafka-0.2.3.dist-info/METADATA
vox_kafka-0.2.3.dist-info/RECORD
